simplememcache/__init__.py
simplememcache/base.py
simplememcache/lru.py
simplememcache/version.py
simplememcache-0.0.0a0.dist-info/LICENSE
simplememcache-0.0.0a0.dist-info/METADATA
simplememcache-0.0.0a0.dist-info/WHEEL
simplememcache-0.0.0a0.dist-info/top_level.txt
simplememcache-0.0.0a0.dist-info/RECORD
