Metadata-Version: 2.1
Name: simplememcache
Version: 0.0.0a0
Summary: Simple mem cache client for python
Home-page: https://github.com/aj-jaiswal007/SimpleMemCache
Author: Amar Jaiswal
Author-email: aj.jaiswal007@gmail.com
Maintainer: aj-jaiswal007
License: MIT License
Keywords: MEMCACHE,CACHE,PYTHON CACHE,SIMPLE CACHE,LRU CACHE
Platform: UNKNOWN
Classifier: Development Status :: 3 - Alpha
Classifier: Intended Audience :: Developers
Classifier: Topic :: Software Development :: Build Tools
Classifier: License :: OSI Approved :: MIT License
Classifier: Operating System :: OS Independent
Classifier: Programming Language :: Python :: 3.6
Classifier: Programming Language :: Python :: 3.7
Classifier: Programming Language :: Python :: 3.8
License-File: LICENSE
Provides-Extra: test
